setup.py
django_ios_push.egg-info/PKG-INFO
django_ios_push.egg-info/SOURCES.txt
django_ios_push.egg-info/dependency_links.txt
django_ios_push.egg-info/top_level.txt
iospush/__init__.py
iospush/admin.py
iospush/models.py
iospush/tests.py
iospush/views.py