Metadata-Version: 1.0
Name: django-ios-push
Version: 0.1.2
Summary: A Django Application for contacting the Apple Push Service and maintaining a list of iOS devices.
Home-page: https://github.com/appsome/django-ios-push
Author: Appsome
Author-email: contact@appsome.co
License: Apache License 2.0
Keywords: django ios push notification
Platform: UNKNOWN
